aircan/__init__.py
aircan/dags/__init__.py
aircan/dags/api_ckan_load_multiple_nodes.py
aircan/dags/api_ckan_load_single_node.py
aircan/dags/hybrid_ckan_load.py
aircan/dependencies/__init__.py
aircan/dependencies/api_load.py
aircan/dependencies/hybrid_load.py
aircan/dependencies/file_conversion/__init__.py
aircan/dependencies/file_conversion/csv_to_json.py
aircan-0.0.4.dist-info/LICENSE.txt
aircan-0.0.4.dist-info/METADATA
aircan-0.0.4.dist-info/WHEEL
aircan-0.0.4.dist-info/top_level.txt
aircan-0.0.4.dist-info/RECORD
