Metadata-Version: 2.1
Name: aircan
Version: 0.0.4
Summary: UNKNOWN
Home-page: UNKNOWN
Author: Datopian
Author-email: info@datopian.com
License: UNKNOWN
Keywords: aircan,airflow,aircan-lib
Platform: UNKNOWN
Requires-Python: <=3.7.8
Requires-Dist: apache-airflow
Requires-Dist: psycopg2
Requires-Dist: python-dotenv
Requires-Dist: requests
Requires-Dist: sqlalchemy
